iva_mt/__init__.py
iva_mt/iva_mt.py
iva_mt/verb_ontology_generator.py
iva_mt-0.2.0.dist-info/LICENSE
iva_mt-0.2.0.dist-info/METADATA
iva_mt-0.2.0.dist-info/WHEEL
iva_mt-0.2.0.dist-info/top_level.txt
iva_mt-0.2.0.dist-info/RECORD
