Metadata-Version: 2.1
Name: iva_mt
Version: 0.2.0
Summary: A machine translation library utilizing m2m100 models, equipped with features for generating diverse verb variants via VerbNet and Conditional Beam Search to enrich Virtual Assistant training sets.
Home-page: https://github.com/cartesinus/iva_mt
Author: cartesinus
Author-email: msowansk@gmail.com
License: MIT
Classifier: Development Status :: 3 - Alpha
Classifier: Intended Audience :: Developers
Classifier: Topic :: Software Development :: Build Tools
Classifier: License :: OSI Approved :: MIT License
Classifier: Programming Language :: Python :: 3
Classifier: Programming Language :: Python :: 3.7
Classifier: Programming Language :: Python :: 3.8
Classifier: Programming Language :: Python :: 3.9
Requires-Python: >=3.7
License-File: LICENSE
Requires-Dist: transformers ==4.28.1
Requires-Dist: sentencepiece ==0.1.99
Requires-Dist: datasets
Requires-Dist: peft
